pythongeneral/__init__.py
pythongeneral/dataProcessing/__init__.py
pythongeneral/dataProcessing/pandas.py
pythongeneral/dataProcessing/string.py
pythongeneral/database/__init__.py
pythongeneral/database/mongo.py
pythongeneral/email/sendEmail.py
pythongeneral/log/__init__.py
pythongeneral/log/logging.py
pythongeneral/model/mongo.py
pythongeneral-0.1.0.dist-info/METADATA
pythongeneral-0.1.0.dist-info/WHEEL
pythongeneral-0.1.0.dist-info/RECORD
