Metadata-Version: 2.1
Name: pythongeneral
Version: 0.1.0
Summary: 
Author: wayne011872
Author-email: wayne011872@gmail.com
Requires-Python: >=3.12,<4.0
Classifier: Programming Language :: Python :: 3
Classifier: Programming Language :: Python :: 3.12
Requires-Dist: loguru (>=0.7.2,<0.8.0)
Requires-Dist: orjson (>=3.10.3,<4.0.0)
Requires-Dist: pandas (>=2.2.2,<3.0.0)
Requires-Dist: pymongo (>=4.7.2,<5.0.0)
Requires-Dist: pyyaml (>=6.0.1,<7.0.0)
